maddlib/__init__.py
maddlib/evaluation.py
maddlib/optimal_bandwidth.py
maddlib/postprocessing/MADD_tools.py
maddlib/postprocessing/__init__.py
maddlib/postprocessing/distribution_examples.py
maddlib/postprocessing/distribution_tools.py
maddlib/postprocessing/postprocessing_tools.py
maddlib/postprocessing/simulation_tools.py
maddlib-1.0.0.dist-info/LICENSE.md
maddlib-1.0.0.dist-info/METADATA
maddlib-1.0.0.dist-info/WHEEL
maddlib-1.0.0.dist-info/top_level.txt
maddlib-1.0.0.dist-info/RECORD
